tvi/solphit/discera/capability/__init__.py
tvi/solphit/discera/capability/code.py
tvi_solphit_discera_capability_code-0.1.3.dist-info/licenses/LICENSE
tvi_solphit_discera_capability_code-0.1.3.dist-info/METADATA
tvi_solphit_discera_capability_code-0.1.3.dist-info/WHEEL
tvi_solphit_discera_capability_code-0.1.3.dist-info/entry_points.txt
tvi_solphit_discera_capability_code-0.1.3.dist-info/top_level.txt
tvi_solphit_discera_capability_code-0.1.3.dist-info/RECORD
